licsber/__init__.py
licsber/env.py
licsber/mongo/__init__.py
licsber/mongo/get_mongo.py
licsber/ql/__init__.py
licsber/ql/send.py
licsber/s3/__init__.py
licsber/s3/get_s3.py
licsber/spider/__init__.py
licsber/spider/get_session.py
licsber-7.0.2.dist-info/METADATA
licsber-7.0.2.dist-info/WHEEL
licsber-7.0.2.dist-info/RECORD
