Metadata-Version: 2.1
Name: licsber
Version: 7.0.2
Project-URL: Homepage, https://licsber.site
Author-email: licsber <admin@licsber.site>
License: GNU Affero General Public License v3 or later (AGPLv3+)
Classifier: License :: OSI Approved :: GNU Affero General Public License v3
Classifier: Operating System :: OS Independent
Requires-Dist: boto3
Requires-Dist: pymongo
Requires-Dist: requests
